benv/__init__.py
benv/cli.py
tests/__init__.py
tests/test_chenv.py
tests/test_lsenv.py
tests/test_mkenv.py
tests/test_rmenv.py
benv-0.1.2.dist-info/LICENSE
benv-0.1.2.dist-info/METADATA
benv-0.1.2.dist-info/WHEEL
benv-0.1.2.dist-info/entry_points.txt
benv-0.1.2.dist-info/top_level.txt
benv-0.1.2.dist-info/RECORD
