Metadata-Version: 2.1
Name: benv
Version: 0.1.2
Summary: A minimalistic Python virtual environment managerthat no one needs
Home-page: https://github.com/burakyilmaz321/benv
Author: Burak Yilmaz
Author-email: burakyilmaz321@gmail.com
License: MIT
Platform: UNKNOWN
Classifier: Programming Language :: Python :: 3
Classifier: License :: OSI Approved :: MIT License
Classifier: Operating System :: OS Independent
Classifier: Development Status :: 1 - Planning
Requires-Python: >=3.6
Requires-Dist: click
